setup.py
py2pyc/__init__.py
py2pyc/py2pyc.py
py2pyc.egg-info/PKG-INFO
py2pyc.egg-info/SOURCES.txt
py2pyc.egg-info/dependency_links.txt
py2pyc.egg-info/top_level.txt