Metadata-Version: 1.0
Name: py2pyc
Version: 1.2
Summary: Compile .py to .pyc With new method
Home-page: https://github.com/SarbazVatan/py2pyc
Author: Soldier_of_iran
Author-email: soldier.of.iran.dev@gmail.com
License: UNKNOWN
Platform: UNKNOWN
